dj_rag_pipeline/__init__.py
dj_rag_pipeline/cli.py
dj_rag_pipeline/templates/project_skeleton/.gitignore
dj_rag_pipeline/templates/project_skeleton/.python-version
dj_rag_pipeline/templates/project_skeleton/README.md
dj_rag_pipeline/templates/project_skeleton/__init__.py
dj_rag_pipeline/templates/project_skeleton/env_example.txt
dj_rag_pipeline/templates/project_skeleton/main.py
dj_rag_pipeline/templates/project_skeleton/pyproject.toml
dj_rag_pipeline/templates/project_skeleton/uv.lock
dj_rag_pipeline/templates/project_skeleton/src/__init__.py
dj_rag_pipeline/templates/project_skeleton/src/data/__init__.py
dj_rag_pipeline/templates/project_skeleton/src/data/markdown_data_pipeline.py
dj_rag_pipeline/templates/project_skeleton/src/data_processing/__init__.py
dj_rag_pipeline/templates/project_skeleton/src/data_processing/check_pincone_index.py
dj_rag_pipeline/templates/project_skeleton/src/data_processing/data_chunking_loading.py
dj_rag_pipeline/templates/project_skeleton/src/data_retriver/__init__.py
dj_rag_pipeline/templates/project_skeleton/src/data_retriver/data_pinecone_retriver.py
dj_rag_pipeline/templates/project_skeleton/src/dj_rag/__init__.py
dj_rag_pipeline/templates/project_skeleton/src/dj_rag/cli.py
dj_rag_pipeline/templates/project_skeleton/src/embeddings/__init__.py
dj_rag_pipeline/templates/project_skeleton/src/embeddings/global_embeddings.py
dj_rag_pipeline/templates/project_skeleton/src/evaluation/__init__.py
dj_rag_pipeline/templates/project_skeleton/src/evaluation/ragas_evaluation.py
dj_rag_pipeline/templates/project_skeleton/src/llm/__init__.py
dj_rag_pipeline/templates/project_skeleton/src/llm/llm_file.py
dj_rag-1.1.0.dist-info/METADATA
dj_rag-1.1.0.dist-info/WHEEL
dj_rag-1.1.0.dist-info/entry_points.txt
dj_rag-1.1.0.dist-info/RECORD
