Metadata-Version: 2.4
Name: dj-rag
Version: 1.1.0
Summary: 🎧 DJ's Production RAG Pipeline - PDFs → Pinecone → LLM → RAGAS (Sub-10s E2E)
Project-URL: Homepage, https://github.com/dhanunjairam/Dj-Rag-Pipeline/tree/dj-rag-pipeline-library
Project-URL: Documentation, https://github.com/dhanunjairam/Dj-Rag-Pipeline/blob/dj-rag-pipeline-library/README.md
Project-URL: Repository, https://github.com/dhanunjairam/Dj-Rag-Pipeline/
Author: DJ
License: MIT
Keywords: fastapi,llm,pdf,pinecone,rag,ragas
Classifier: Development Status :: 5 - Production/Stable
Classifier: Intended Audience :: Developers
Classifier: License :: OSI Approved :: MIT License
Classifier: Programming Language :: Python :: 3.13
Classifier: Topic :: Software Development :: Libraries :: Python Modules
Requires-Python: >=3.13
Requires-Dist: apscheduler>=3.11.2
Requires-Dist: docling>=2.66.0
Requires-Dist: einops>=0.8.1
Requires-Dist: fastapi>=0.128.0
Requires-Dist: gunicorn>=23.0.0
Requires-Dist: langchain-classic>=1.0.1
Requires-Dist: langchain-core>=1.2.6
Requires-Dist: langchain-huggingface>=1.2.0
Requires-Dist: langchain-openai>=1.1.7
Requires-Dist: langchain-text-splitters>=1.1.0
Requires-Dist: langchain>=1.2.2
Requires-Dist: litellm>=1.80.12
Requires-Dist: nest-asyncio>=1.6.0
Requires-Dist: pinecone[asyncio]>=8.0.0
Requires-Dist: python-multipart>=0.0.21
Requires-Dist: ragas>=0.4.2
Requires-Dist: sentence-transformers>=5.2.0
Requires-Dist: torch>=2.9.1
Requires-Dist: twine>=6.2.0
Requires-Dist: uvicorn>=0.40.0
Provides-Extra: dev
Requires-Dist: black>=23.0.0; extra == 'dev'
Requires-Dist: pytest>=7.4.0; extra == 'dev'
Requires-Dist: ruff>=0.1.0; extra == 'dev'
